[
  {
    "question": "Δίνεται ένα γράφημα με 10 κορυφές και 11 ακμές. Ποιες από τις παρακάτω προτάσεις ισχύουν πάντα;",
    "answers": [
      {
        "text": "Το γράφημα είναι επίπεδο.",
        "correct": false,
        "description": ""
      },
      {
        "text": "Αν το γράφημα δεν είναι επίπεδο, τότε το συμπλήρωμα του είναι επίπεδο.",
        "correct": false,
        "description": ""
      },
      {
        "text": "Το γράφημα περιέχει κύκλο.",
        "correct": true,
        "description": ""
      },
      {
        "text": "Αν το γράφημα είναι επίπεδο και συνεκτικό τότε κάθε εμβάπτιση του έχει ακριβώς τρεις όψεις.",
        "correct": true,
        "description": ""
      },
      {
        "text": "Έστω ότι το γράφημα είναι συνεκτικό. Αποκλείεται να περιέχει κύκλο Euler.",
        "correct": false,
        "description": ""
      }
    ]
  }
]
